pyfun_events/__init__.py
pyfun_events/config.py
pyfun_events/run.py
pyfun_events-0.2.1.dist-info/LICENSE
pyfun_events-0.2.1.dist-info/METADATA
pyfun_events-0.2.1.dist-info/WHEEL
pyfun_events-0.2.1.dist-info/top_level.txt
pyfun_events-0.2.1.dist-info/RECORD
