Metadata-Version: 2.1
Name: pyfun-events
Version: 0.2.1
Summary: UNKNOWN
Home-page: https://github.com/pypa/sampleproject
License: UNKNOWN
Platform: UNKNOWN
Classifier: Programming Language :: Python :: 3
Classifier: License :: OSI Approved :: Apache Software License
Classifier: Operating System :: Unix
Requires-Dist: cloudevents (<0.3,>=0.2.1)
Requires-Dist: Flask (<2,>=1.0.2)
Requires-Dist: ujson (<2,>=1.35)
